gs_prompt_manager/__init__.py
gs_prompt_manager/prompt_base.py
gs_prompt_manager/prompt_manager.py
gs_prompt_manager-0.0.4.dist-info/licenses/LICENSE
gs_prompt_manager-0.0.4.dist-info/METADATA
gs_prompt_manager-0.0.4.dist-info/WHEEL
gs_prompt_manager-0.0.4.dist-info/top_level.txt
gs_prompt_manager-0.0.4.dist-info/RECORD
