Metadata-Version: 2.4
Name: gs_prompt_manager
Version: 0.0.4
Summary: A prompt manager that auto collect python class inherenting PromptBase.
Author: Guan Huang
License-Expression: Apache-2.0
Classifier: Programming Language :: Python :: 3
Classifier: Operating System :: OS Independent
Requires-Python: >=3.7
License-File: LICENSE
Dynamic: license-file
